hatch_robotpy/__init__.py
hatch_robotpy/_version.py
hatch_robotpy/config.py
hatch_robotpy/download.py
hatch_robotpy/from_vendor.py
hatch_robotpy/hooks.py
hatch_robotpy/maven.py
hatch_robotpy/platforms.py
hatch_robotpy/plugin.py
hatch_robotpy/validate.py
hatch_robotpy-0.2.1.dist-info/METADATA
hatch_robotpy-0.2.1.dist-info/WHEEL
hatch_robotpy-0.2.1.dist-info/entry_points.txt
hatch_robotpy-0.2.1.dist-info/licenses/LICENSE.txt
hatch_robotpy-0.2.1.dist-info/RECORD
