Metadata-Version: 2.4
Name: hatch-robotpy
Version: 0.2.1
Summary: Hatchling plugins for use with RobotPy projects
Project-URL: Source code, https://github.com/robotpy/hatch-robotpy
Author-email: Dustin Spicuzza <dustin@virtualroadside.com>
License-Expression: BSD-3-Clause
License-File: LICENSE.txt
Keywords: hatch,robotpy
Classifier: Framework :: Hatch
Requires-Python: >=3.8
Requires-Dist: distro; platform_system == 'Linux'
Requires-Dist: hatchling
Requires-Dist: packaging
Requires-Dist: validobj~=1.2
